{
  "profile": "data-package",
  "name": "ispb-participants-catalog",
  "id": "https://github.com/cafeinadesign/ispb-participants",
  "title": "ISPB Participants Catalog",
  "description": "ISPB Participants Catalog - Catálogo público derivado de fonte oficial do Banco Central. Static versioned artifacts are distributed from current/ and snapshots/.",
  "licenses": [
    {
      "name": "ODC-By-1.0",
      "title": "Open Data Commons Attribution License 1.0",
      "path": "https://opendatacommons.org/licenses/by/1-0/"
    }
  ],
  "sources": [
    {
      "path": "https://www.bcb.gov.br/estabilidadefinanceira/sistemapagamentosinstantaneos"
    },
    {
      "path": "https://www.bcb.gov.br/api/paginasite/sitebcb/estabilidadefinanceira/sistemapagamentosinstantaneos"
    },
    {
      "path": "https://www.bcb.gov.br/content/estabilidadefinanceira/spi-pdf/participantes-spi-20260610.pdf"
    },
    {
      "path": "https://www.bcb.gov.br/content/estabilidadefinanceira/spi/participantes-spi-20260610.csv"
    },
    {
      "path": "https://www.bcb.gov.br/estabilidadefinanceira/pix-participantes"
    },
    {
      "path": "https://www.bcb.gov.br/api/paginasite/sitebcb/estabilidadefinanceira/pix-participantes"
    },
    {
      "path": "https://www.bcb.gov.br/content/estabilidadefinanceira/participantes_pix_pdf/lista-participantes-instituicoes-em-adesao-pix-20260610.pdf"
    },
    {
      "path": "https://www.bcb.gov.br/content/estabilidadefinanceira/participantes_pix/lista-participantes-instituicoes-em-adesao-pix-20260610.csv"
    }
  ],
  "resources": [
    {
      "name": "spi_participants_csv",
      "path": "current/spi_participants.csv",
      "format": "csv",
      "mediatype": "text/csv",
      "schema": "schemas/spi_participants.schema.json",
      "hash": "5e1f47539f669695f35ef5985c4d38c5ed31c652c032c95547fa4507857bfce8",
      "bytes": 621108,
      "rows": 884
    },
    {
      "name": "spi_participants_json",
      "path": "current/spi_participants.json",
      "format": "json",
      "mediatype": "application/json",
      "schema": "schemas/spi_participants.schema.json",
      "hash": "e2855c2ccd24de12ace2b1d811675259ba66c4bba77d3a400b5c4f3f9b8d4a56",
      "bytes": 1130569,
      "rows": 884
    },
    {
      "name": "pix_active_participants_csv",
      "path": "current/pix_active_participants.csv",
      "format": "csv",
      "mediatype": "text/csv",
      "schema": "schemas/pix_active_participants.schema.json",
      "hash": "794125e725a85ecec02c2302b2c5d593beb75ba15031fee9d48b4c655a36d10e",
      "bytes": 757366,
      "rows": 901
    },
    {
      "name": "pix_active_participants_json",
      "path": "current/pix_active_participants.json",
      "format": "json",
      "mediatype": "application/json",
      "schema": "schemas/pix_active_participants.schema.json",
      "hash": "5149bfeb97952b83a71148355c0c822a07bda7c05ad9658c264936bf98cd3d3e",
      "bytes": 1237920,
      "rows": 901
    },
    {
      "name": "pix_in_adhesion_csv",
      "path": "current/pix_in_adhesion.csv",
      "format": "csv",
      "mediatype": "text/csv",
      "schema": "schemas/pix_in_adhesion.schema.json",
      "hash": "8d54dba0b31181373f1499cbb292712808d271b83b48deff89447d0e145e022d",
      "bytes": 15215,
      "rows": 19
    },
    {
      "name": "pix_in_adhesion_json",
      "path": "current/pix_in_adhesion.json",
      "format": "json",
      "mediatype": "application/json",
      "schema": "schemas/pix_in_adhesion.schema.json",
      "hash": "742710d9e75c14708b637be3d4dee81f0932c37576f11a1abac1a7c0f83099d5",
      "bytes": 24095,
      "rows": 19
    },
    {
      "name": "catalog_crosswalk_csv",
      "path": "current/catalog_crosswalk.csv",
      "format": "csv",
      "mediatype": "text/csv",
      "schema": "schemas/catalog_crosswalk.schema.json",
      "hash": "1d39f81b323c985a5c2765b37060071a06c7dbad337d1b6afa860060b62232ab",
      "bytes": 616871,
      "rows": 1804
    },
    {
      "name": "catalog_crosswalk_json",
      "path": "current/catalog_crosswalk.json",
      "format": "json",
      "mediatype": "application/json",
      "schema": "schemas/catalog_crosswalk.schema.json",
      "hash": "e5b82b11963652b5c2bd7b17c960ca7d2996a40b57e9c71fbb79b246aa519bd1",
      "bytes": 1327213,
      "rows": 1804
    },
    {
      "name": "manifest_json",
      "path": "current/manifest.json",
      "format": "json",
      "mediatype": "application/json",
      "hash": "1791ebe3470cc08ec19f5b36631b9d74aa73abda61d85ebb07e085c576905c09",
      "bytes": 4575
    }
  ]
}
